deal/__init__.py
deal/__main__.py
deal/_cached_property.py
deal/_colors.py
deal/_exceptions.py
deal/_imports.py
deal/_mem_test.py
deal/_schemes.py
deal/_source.py
deal/_sphinx.py
deal/_state.py
deal/_testing.py
deal/_trace.py
deal/_types.py
deal/mypy.py
deal/py.typed
deal/_cli/__init__.py
deal/_cli/_base.py
deal/_cli/_common.py
deal/_cli/_decorate.py
deal/_cli/_lint.py
deal/_cli/_main.py
deal/_cli/_memtest.py
deal/_cli/_prove.py
deal/_cli/_stub.py
deal/_cli/_test.py
deal/_runtime/__init__.py
deal/_runtime/_contracts.py
deal/_runtime/_decorators.py
deal/_runtime/_dispatch.py
deal/_runtime/_has_patcher.py
deal/_runtime/_inherit.py
deal/_runtime/_invariant.py
deal/_runtime/_validators.py
deal/introspection/__init__.py
deal/introspection/_extractor.py
deal/introspection/_wrappers.py
deal/linter/__init__.py
deal/linter/__main__.py
deal/linter/_checker.py
deal/linter/_contract.py
deal/linter/_error.py
deal/linter/_func.py
deal/linter/_rules.py
deal/linter/_stub.py
deal/linter/_template.py
deal/linter/_transformer.py
deal/linter/_extractors/__init__.py
deal/linter/_extractors/asserts.py
deal/linter/_extractors/common.py
deal/linter/_extractors/contracts.py
deal/linter/_extractors/definitions.py
deal/linter/_extractors/examples.py
deal/linter/_extractors/exceptions.py
deal/linter/_extractors/imports.py
deal/linter/_extractors/markers.py
deal/linter/_extractors/pre.py
deal/linter/_extractors/result.py
deal/linter/_extractors/returns.py
deal/linter/_extractors/value.py
deal/linter/stubs/aiohttp/base_protocol.json
deal/linter/stubs/aiohttp/client.json
deal/linter/stubs/aiohttp/client_reqrep.json
deal/linter/stubs/aiohttp/client_ws.json
deal/linter/stubs/aiohttp/connector.json
deal/linter/stubs/aiohttp/cookiejar.json
deal/linter/stubs/aiohttp/formdata.json
deal/linter/stubs/aiohttp/helpers.json
deal/linter/stubs/aiohttp/http_parser.json
deal/linter/stubs/aiohttp/http_websocket.json
deal/linter/stubs/aiohttp/http_writer.json
deal/linter/stubs/aiohttp/locks.json
deal-4.24.3.dist-info/entry_points.txt
deal-4.24.3.dist-info/LICENSE
deal-4.24.3.dist-info/WHEEL
deal-4.24.3.dist-info/METADATA
deal-4.24.3.dist-info/RECORD
