Metadata-Version: 2.1
Name: deal
Version: 4.24.3
Summary: **Deal** is a Python library for [design by contract][wiki] (DbC) programming.
Home-page: https://github.com/life4/deal
License: MIT
Keywords: deal,contracts,pre,post,invariant,decorators,validation,pythonic,functional
Author: Gram
Author-email: gram@orsinium.dev
Requires-Python: >=3.8
Classifier: Development Status :: 5 - Production/Stable
Classifier: Environment :: Plugins
Classifier: Intended Audience :: Developers
Classifier: License :: OSI Approved :: MIT License
Classifier: Programming Language :: Python
Classifier: Topic :: Software Development
Classifier: Topic :: Software Development :: Libraries :: Python Modules
Classifier: Topic :: Software Development :: Quality Assurance
Requires-Dist: astroid>=2.11.0 ; extra == "all"
Requires-Dist: deal-solver>=0.1.2 ; extra == "all"
Requires-Dist: hypothesis ; extra == "all"
Requires-Dist: pygments ; extra == "all"
Requires-Dist: typeguard>=3.0.0 ; extra == "all"
Requires-Dist: vaa>=0.2.1 ; extra == "all"
Requires-Dist: m2r2 ; extra == "docs"
Requires-Dist: myst-parser ; extra == "docs"
Requires-Dist: sphinx==3.5.* ; extra == "docs"
Requires-Dist: sphinx-rtd-theme==0.5.* ; extra == "docs"
Requires-Dist: astroid>=2.11.0 ; extra == "integration"
Requires-Dist: deal-solver>=0.1.2 ; extra == "integration"
Requires-Dist: hypothesis ; extra == "integration"
Requires-Dist: pygments ; extra == "integration"
Requires-Dist: typeguard<4.0.0 ; extra == "integration"
Requires-Dist: vaa>=0.2.1 ; extra == "integration"
Requires-Dist: sphinx>=4.5.0 ; extra == "integration"
Requires-Dist: flake8 ; extra == "integration"
Requires-Dist: marshmallow ; extra == "integration"
Requires-Dist: flake8 ; extra == "lint"
Requires-Dist: flake8-commas ; extra == "lint"
Requires-Dist: flake8-quotes ; extra == "lint"
Requires-Dist: mypy>=0.900 ; extra == "lint"
Requires-Dist: mypy_test>=0.1.1 ; extra == "lint"
Requires-Dist: isort ; extra == "lint"
Requires-Dist: unify ; extra == "lint"
Requires-Dist: deal-solver>=0.1.2 ; extra == "lint"
Requires-Dist: hypothesis ; extra == "lint"
Requires-Dist: pygments ; extra == "lint"
Requires-Dist: typeguard<4.0.0 ; extra == "lint"
Requires-Dist: coverage[toml] ; extra == "test"
Requires-Dist: coverage-conditional-plugin ; extra == "test"
Requires-Dist: docstring-parser ; extra == "test"
Requires-Dist: pytest-cov ; extra == "test"
Requires-Dist: pytest ; extra == "test"
Requires-Dist: urllib3 ; extra == "test"
Provides-Extra: all
Provides-Extra: docs
Provides-Extra: integration
Provides-Extra: lint
Provides-Extra: test
